LICENSE
MANIFEST.in
README.md
pyproject.toml
setup.py
src/lightspot/__init__.py
src/lightspot/gmacula.py
src/lightspot/gsampler.py
src/lightspot/macula.cpp
src/lightspot/priors.py
src/lightspot/sampler.py
src/lightspot/utils.py
src/lightspot.egg-info/PKG-INFO
src/lightspot.egg-info/SOURCES.txt
src/lightspot.egg-info/dependency_links.txt
src/lightspot.egg-info/requires.txt
src/lightspot.egg-info/top_level.txt
tests/test_macula.py
tests/test_model.py
tests/test_priors.py
tests/test_sampler.py