Metadata-Version: 2.1
Name: lightspot
Version: 1.0b3
Summary: Modelization of light curves from spotted stars
Home-page: https://github.com/dioph/lightspot
Author: Eduardo Nunes
Author-email: dioph@pm.me
License: MIT
Classifier: Programming Language :: Python :: 3
Classifier: License :: OSI Approved :: MIT License
Classifier: Operating System :: OS Independent
Classifier: Intended Audience :: Science/Research
License-File: LICENSE
Requires-Dist: dynesty>=1.0
Requires-Dist: h5py
Requires-Dist: matplotlib
Requires-Dist: scipy>=0.19
Requires-Dist: ultranest>=3.0
Provides-Extra: cuda
Requires-Dist: cupy; extra == "cuda"
Requires-Dist: numba; extra == "cuda"
Provides-Extra: docs
Requires-Dist: jupyter>=1.0; extra == "docs"
Requires-Dist: myst-nb>=0.17; extra == "docs"
Requires-Dist: numpydoc; extra == "docs"
Requires-Dist: pydata-sphinx-theme; extra == "docs"
Provides-Extra: test
Requires-Dist: black==22.3.0; extra == "test"
Requires-Dist: flake8; extra == "test"
Requires-Dist: isort; extra == "test"
Requires-Dist: pytest; extra == "test"
Requires-Dist: pytest-cov; extra == "test"
Requires-Dist: tox; extra == "test"
